django_include-0.2.4.dist-info/DESCRIPTION.rst
django_include-0.2.4.dist-info/METADATA
django_include-0.2.4.dist-info/RECORD
django_include-0.2.4.dist-info/WHEEL
django_include-0.2.4.dist-info/metadata.json
django_include-0.2.4.dist-info/top_level.txt
include/__init__.py
include/aggregations.py
include/expressions.py
include/manager.py
include/query.py
include/util.py
