Metadata-Version: 2.0
Name: django-include
Version: 0.2.4
Summary: ORM extensions for performance-conscious perfectionists.
Home-page: http://github.com/chrisseto/django-include
Author: Chris Seto
Author-email: chriskseto@gmail.com
License: MIT
Keywords: django,postgres,sql,optimization,performance
Platform: UNKNOWN
Classifier: Operating System :: OS Independent
Classifier: Programming Language :: Python
Classifier: Programming Language :: Python :: 2
Classifier: Programming Language :: Python :: 2.7
Classifier: Programming Language :: Python :: 3
Classifier: Programming Language :: Python :: 3.5
Classifier: Programming Language :: Python :: 3.6
Classifier: Framework :: Django
Classifier: Framework :: Django :: 1.9
Classifier: Framework :: Django :: 1.10
Classifier: Framework :: Django :: 1.11
Classifier: Environment :: Web Environment
Classifier: Intended Audience :: Developers
Classifier: Topic :: Internet :: WWW/HTTP
Classifier: Topic :: Software Development :: Libraries :: Python Modules
Requires-Dist: psycopg2
Provides-Extra: faster
Requires-Dist: ciso8601; extra == 'faster'
Requires-Dist: ujson; extra == 'faster'
